pgevents/__init__.py
pgevents/app.py
pgevents/cli.py
pgevents/constants.py
pgevents/context.py
pgevents/data_access.py
pgevents/event.py
pgevents/event_stream.py
pgevents/version.py
pgevents/migrations/20200704_2145_migration_create_event_table/apply.sql
pgevents/migrations/20200704_2145_migration_create_event_table/rollback.sql
pgevents/utils/__init__.py
pgevents/utils/app_loader.py
pgevents/utils/timestamps.py
pgevents-0.0.12.dist-info/LICENSE
pgevents-0.0.12.dist-info/METADATA
pgevents-0.0.12.dist-info/WHEEL
pgevents-0.0.12.dist-info/entry_points.txt
pgevents-0.0.12.dist-info/top_level.txt
pgevents-0.0.12.dist-info/RECORD
