Metadata-Version: 2.1
Name: pgevents
Version: 0.0.12
Summary: Python event framework using PostgreSQL listen/notify
Home-page: https://github.com/peajayni/pgevents
License: UNKNOWN
Platform: UNKNOWN
Requires-Python: >=3.7
Requires-Dist: psycopg2-binary
Requires-Dist: pgmigrations
Requires-Dist: click
